staples_lang/__init__.py
staples_lang/__main__.py
staples_lang/cli.py
staples_lang-1.2.6.dist-info/METADATA
staples_lang-1.2.6.dist-info/WHEEL
staples_lang-1.2.6.dist-info/entry_points.txt
staples_lang-1.2.6.dist-info/RECORD
