Metadata-Version: 2.3
Name: staples-lang
Version: 1.2.6
Summary: Staples is an esoteric language designed to give all developers a headache.
License: MIT
Author: SeafoodStudios
Requires-Python: >=3.10
Classifier: License :: OSI Approved :: MIT License
Classifier: Programming Language :: Python :: 3
Classifier: Programming Language :: Python :: 3.10
Classifier: Programming Language :: Python :: 3.11
Classifier: Programming Language :: Python :: 3.12
Classifier: Programming Language :: Python :: 3.13
